IntegerWords.py
IntegerWords-1.0.dist-info/LICENSE
IntegerWords-1.0.dist-info/METADATA
IntegerWords-1.0.dist-info/WHEEL
IntegerWords-1.0.dist-info/entry_points.txt
IntegerWords-1.0.dist-info/top_level.txt
IntegerWords-1.0.dist-info/RECORD
