Metadata-Version: 2.1
Name: IntegerWords
Version: 1.0
Summary: A python3 module that converts numbers to English words.  For example "5" -> "five"
Home-page: https://github.com/deadmund/IntegerWords
Author: Ed Novak
Author-email: enovak@fandm.edu
License: GPL-v3
Classifier: Programming Language :: Python :: 3
Classifier: License :: OSI Approved :: GNU General Public License v3 (GPLv3)
Classifier: Operating System :: OS Independent
Requires-Python: >=3.0
License-File: LICENSE
